pgmagick/__init__.py
pgmagick/_pgmagick.cpython-36m-darwin.so
pgmagick/_version.py
pgmagick/api.py
pgmagick-0.7.4.dist-info/METADATA
pgmagick-0.7.4.dist-info/RECORD
pgmagick-0.7.4.dist-info/WHEEL
pgmagick-0.7.4.dist-info/top_level.txt
