Metadata-Version: 2.1
Name: pgmagick
Version: 0.7.4
Summary: Yet Another Python wrapper for GraphicsMagick
Home-page: https://github.com/hhatto/pgmagick
Author: Hideo Hattori
Author-email: hhatto.jp@gmail.com
License: MIT
Keywords: GraphicsMagick ImageMagick graphics boost image
Platform: UNKNOWN
Classifier: Development Status :: 4 - Beta
Classifier: Intended Audience :: Developers
Classifier: License :: OSI Approved :: MIT License
Classifier: Operating System :: POSIX
Classifier: Programming Language :: C++
Classifier: Programming Language :: Python
Classifier: Programming Language :: Python :: 3
Classifier: Topic :: Multimedia :: Graphics
